neo_vendors/__init__.py
neo_vendors/date_time.py
neo_vendors/fastapi_tools/__init__.py
neo_vendors/fastapi_tools/errors/__init__.py
neo_vendors/fastapi_tools/errors/base.py
neo_vendors/fastapi_tools/errors/exceptions.py
neo_vendors/fastapi_tools/errors/handlers.py
neo_vendors/fastapi_tools/errors/payloads.py
neo_vendors/fastapi_tools/middlewares/__init__.py
neo_vendors/fastapi_tools/middlewares/request_handler_middleware.py
neo_vendors/fastapi_tools/request_context.py
neo_vendors/http/__init__.py
neo_vendors/http/async_transport.py
neo_vendors/http/http_methods.py
neo_vendors/http/request_context.py
neo_vendors/http/sync_transport.py
neo_vendors/loggers.py
neo_vendors/numbers.py
neo_vendors/telegram_log/__init__.py
neo_vendors/telegram_log/handler.py
neo_vendors-0.9.15.dist-info/METADATA
neo_vendors-0.9.15.dist-info/WHEEL
neo_vendors-0.9.15.dist-info/RECORD
