Metadata-Version: 2.1
Name: neo-vendors
Version: 0.9.15
Summary: 
Author: ruslangilfanov
Author-email: rgilfanov@fix.ru
Requires-Python: >=3.10,<4.0
Classifier: Programming Language :: Python :: 3
Classifier: Programming Language :: Python :: 3.10
Classifier: Programming Language :: Python :: 3.11
Requires-Dist: aiohttp (>=3.8.4,<4.0.0)
Requires-Dist: black (>=23.1.0,<24.0.0)
Requires-Dist: environs (>=9.5.0,<10.0.0)
Requires-Dist: flake8 (>=6.0.0,<7.0.0)
Requires-Dist: mypy (>=1.0.1,<2.0.0)
Requires-Dist: pendulum (>=2.1.2,<3.0.0)
Requires-Dist: pytelegrambotapi (>=4.10.0,<5.0.0)
Requires-Dist: pytest (>=7.2.1,<8.0.0)
Requires-Dist: requests (>=2.28.2,<3.0.0)
Requires-Dist: sentry-sdk[fastapi,sqlalchemy] (>=1.16.0,<2.0.0)
Requires-Dist: types-requests (>=2.28.11.17,<3.0.0.0)
